[
  {
    "name" : "Argleton County Council",
    "shortName": "Argleton",
    "parkingBoundary": "Argleton City Centre",
    "permitMax": "four",
    "permitsCosts": [51, 81, 153, 153],
    "permitWait": 5,
    "string" : "argleton"
  },
  {
    "name" : "Cambridgeshire County Council",
    "shortName": "Cambridgeshire",
    "parkingBoundary": "Cambridgeshire city centre",
    "permitMax": "unlimited",
    "permitsCosts": [51,61,71,120],
    "permitWait": 5,
    "string" : "cambridgeshire"
  },
  {
    "name" : "Unbrandedland Council",
    "shortName" : "Unbrandedland",
    "parkingBoundary" : "Unbrandedland City",
    "permitMax": "sixty seven",
    "permitsCosts": [67, 77, 100, 100],
    "permitWait": 0,
    "string" : "unbranded"
  }
]
